YeluBoyilunBijiQuan24JiangV20ApolloGabriel/README.md
YeluBoyilunBijiQuan24JiangV20ApolloGabriel/__init__.py
YeluBoyilunBijiQuan24JiangV20ApolloGabriel/__main__.py
YeluBoyilunBijiQuan24JiangV20ApolloGabriel/file.pdf
YeluBoyilunBijiQuan24JiangV20ApolloGabriel/index.html
yelu_boyilun_biji_quan_24_jiang_v2_0_apollo_gabriel-2024.3.3.0.dist-info/METADATA
yelu_boyilun_biji_quan_24_jiang_v2_0_apollo_gabriel-2024.3.3.0.dist-info/WHEEL
yelu_boyilun_biji_quan_24_jiang_v2_0_apollo_gabriel-2024.3.3.0.dist-info/entry_points.txt
yelu_boyilun_biji_quan_24_jiang_v2_0_apollo_gabriel-2024.3.3.0.dist-info/top_level.txt
yelu_boyilun_biji_quan_24_jiang_v2_0_apollo_gabriel-2024.3.3.0.dist-info/RECORD
